odoo/addons/web_m2x_options_manager/README.rst
odoo/addons/web_m2x_options_manager/__init__.py
odoo/addons/web_m2x_options_manager/__manifest__.py
odoo/addons/web_m2x_options_manager/demo/res_partner_demo_view.xml
odoo/addons/web_m2x_options_manager/i18n/it.po
odoo/addons/web_m2x_options_manager/i18n/web_m2x_options_manager.pot
odoo/addons/web_m2x_options_manager/models/__init__.py
odoo/addons/web_m2x_options_manager/models/ir_model.py
odoo/addons/web_m2x_options_manager/models/ir_ui_view.py
odoo/addons/web_m2x_options_manager/models/m2x_create_edit_option.py
odoo/addons/web_m2x_options_manager/readme/CONTRIBUTORS.rst
odoo/addons/web_m2x_options_manager/readme/DESCRIPTION.rst
odoo/addons/web_m2x_options_manager/readme/USAGE.rst
odoo/addons/web_m2x_options_manager/security/ir.model.access.csv
odoo/addons/web_m2x_options_manager/static/description/icon.png
odoo/addons/web_m2x_options_manager/static/description/index.html
odoo/addons/web_m2x_options_manager/tests/__init__.py
odoo/addons/web_m2x_options_manager/tests/test_m2x_create_edit_option.py
odoo/addons/web_m2x_options_manager/views/ir_model.xml
odoo14_addon_web_m2x_options_manager-14.0.1.4.0.dist-info/METADATA
odoo14_addon_web_m2x_options_manager-14.0.1.4.0.dist-info/WHEEL
odoo14_addon_web_m2x_options_manager-14.0.1.4.0.dist-info/top_level.txt
odoo14_addon_web_m2x_options_manager-14.0.1.4.0.dist-info/RECORD
