Metadata-Version: 2.1
Name: odoo14-addon-web_m2x_options_manager
Version: 14.0.1.4.0
Summary: Adds an interface to manage the "Create" and "Create and Edit" options for specific models and fields.
Home-page: https://github.com/OCA/web
Author: Camptocamp, Odoo Community Association (OCA)
Author-email: support@odoo-community.org
License: AGPL-3
Classifier: Programming Language :: Python
Classifier: Framework :: Odoo
Classifier: Framework :: Odoo :: 14.0
Classifier: License :: OSI Approved :: GNU Affero General Public License v3
Requires-Python: >=3.6
Requires-Dist: odoo14-addon-web-m2x-options
Requires-Dist: odoo<14.1dev,>=14.0a
